gsb/__init__.py
gsb/_git.py
gsb/_make_zip_archive.py
gsb/_version.py
gsb/backup.py
gsb/cli.py
gsb/export.py
gsb/fastforward.py
gsb/history.py
gsb/logging.py
gsb/manifest.py
gsb/onboard.py
gsb/py.typed
gsb/rewind.py
gsb/test/__init__.py
gsb/test/conftest.py
gsb/test/test_backup.py
gsb/test/test_delete.py
gsb/test/test_export.py
gsb/test/test_history.py
gsb/test/test_init.py
gsb/test/test_rewind.py
gsb-0.0.5.dist-info/licenses/LICENSE
gsb-0.0.5.dist-info/METADATA
gsb-0.0.5.dist-info/WHEEL
gsb-0.0.5.dist-info/entry_points.txt
gsb-0.0.5.dist-info/top_level.txt
gsb-0.0.5.dist-info/RECORD
