Metadata-Version: 2.4
Name: gsb
Version: 0.0.5
Summary: Game Save Backups: A Git-Based Tool for Managing Your Save States
Home-page: https://github.com/OpenBagTwo/gsb
Author: Gili "OpenBagTwo" Barlev
License: GPL v3
Requires-Python: >=3.11
License-File: LICENSE
Requires-Dist: pygit2>=1.15
Requires-Dist: click>=8
Requires-Dist: pathvalidate>=2.5
Provides-Extra: test
Requires-Dist: pytest>=7; extra == "test"
Requires-Dist: pytest-cov>=4; extra == "test"
Dynamic: author
Dynamic: description
Dynamic: description-content-type
Dynamic: home-page
Dynamic: license
Dynamic: license-file
Dynamic: provides-extra
Dynamic: requires-dist
Dynamic: requires-python
Dynamic: summary
